{"$START$": {"Google": 1, "President": 1, "Hurricane": 1, "GE\u2019s": 1, "U.S.": 1, "There": 1, "Elliott": 1, "German": 1, "The": 5, "Ford": 1, "Hedge": 1, "A": 2, "Many": 1, "New": 1, "Rapid,": 1, "Indonesia": 1, "Human": 1, "Rep.": 1, "Since": 1, "Drug": 1, "Employers": 1, "Chinese": 1, "Saving": 1, "October": 24, "At": 1}, "Google": {"exposed": 1}, "exposed": {"the": 1}, "the": {"private": 1, "Google+": 1, "issue": 1, "No.": 1, "coast": 1, "Florida": 2, "U.S.": 1, "shareholder-activism": 1, "hedge": 1, "companies": 1, "grain": 1, "rally": 1, "oil": 1, "trading": 1, "third": 1, "economy": 2, "search": 1, "organization": 1, "upstate": 1, "required": 1, "writers": 1, "big": 1, "measure": 1, "polls": 1, "ranks": 1, "run.": 1, "coming": 1, "stakes.": 1, "head": 1, "accusations.": 1, "next": 1, "opportunity": 1, "key.": 1, "minimum": 1, "Catholic": 1, "pope": 1, "Church": 1, "U.N.,": 1, "global": 1, "red": 1, "biggest": 1, "uncertainty": 1, "underlying": 1, "polls.": 1, "beauty": 1, "tech": 1, "defensive,": 1, "passengers": 1, "outcome": 1, "world": 1, "secretary": 1, "meeting": 1, "last": 1, "nation's": 1, "same": 1, "Scottish": 1, "Saudi": 1, "allegations,": 1, "death": 1, "quake": 1, "key": 1, "source": 1, "West": 1, "day": 1, "show's": 1, "city": 1, "constitution.": 1}, "private": {"data": 1}, "data": {"of": 1, "privacy": 1}, "of": {"hundreds": 1, "thousands": 1, "users": 1, "the": 3, "misuse.": 1, "fears": 1, "confidence": 1, "Cuba": 1, "State": 1, "bilateral": 1, "individual": 1, "Volkswagen\u2019s": 1, "falsifying": 1, "improving": 1, "bets": 1, "oil": 1, "society": 1, "people": 2, "mud": 1, "women": 1, "counterfeit": 1, "medications": 1, "Interpol": 1, "bribery,": 1, "lightning-rod": 1, "mental": 1, "bishops": 1, "previous": 1, "sleeplessness.": 1, "Congress,": 1, "a": 1, "state": 1, "claiming": 1, "soccer": 1, "its": 2, "houses.": 1, "technology": 1, "Brett": 1, "several": 1}, "hundreds": {"of": 1}, "thousands": {"of": 3}, "users": {"of": 1}, "Google+": {"social": 1}, "social": {"network,": 1}, "network,": {"though": 1}, "though": {"it": 1}, "it": {"didn\u2019t": 1, "steamed": 1, "was": 3, "targets.": 1, "heads": 1, "fits.": 1, "in": 1}, "didn\u2019t": {"find": 1, "have": 1}, "find": {"evidence": 1}, "evidence": {"of": 1}, "misuse.": {"The": 1}, "The": {"company": 1, "plywood": 1, "two": 1, "Ensco-Rowan": 1, "Nobel": 1, "limousine": 1, "author\u2019s": 1, "storm": 1, "newly": 1, "new": 1, "photos": 1, "driver,": 1}, "company": {"opted": 1}, "opted": {"not": 1}, "not": {"to": 1}, "to": {"disclose": 1, "fire": 1, "the": 4, "strike": 1, "name": 1, "wonder": 1, "jeopardize": 1, "identify": 1, "obtain": 1, "be": 3, "South": 1, "WPP.": 1, "make": 2, "limit": 1, "announce": 1, "almost": 1, "avoid": 1, "do,": 1, "a": 2, "pursue": 1, "his": 1, "stop": 1, "strengthen": 1, "weigh": 1, "getting": 1, "share": 1, "meet": 1, "keep": 1, "replace": 1, "apps": 1, "help": 2, "craft": 1, "representing": 1, "wealth": 1, "technology,": 1, "one": 1, "two-thirds": 1, "automation": 1, "ban": 1}, "disclose": {"the": 1}, "issue": {"this": 1}, "this": {"past": 1, "year": 2, "week.": 2, "month.": 1, "week": 1}, "past": {"spring,": 1, "a": 1}, "spring,": {"in": 1}, "in": {"part": 1, "Beijing": 1, "point.": 1, "Bunge": 1, "pushing": 1, "their": 1, "the": 6, "Economic": 1, "mountains": 1, "September": 1, "a": 1, "2016,": 1, "investor": 1, "on": 1, "Lyon": 1, "touch": 1, "Rome": 1, "search": 1, "Europe": 1, "Schoharie,": 1, "Portuguese.": 1, "Istanbul.": 1, "areas": 1, "full": 1, "Saturday": 1, "civil": 1}, "part": {"because": 1}, "because": {"of": 1, "there": 1}, "fears": {"doing": 1}, "doing": {"so": 1, "or": 1}, "so": {"would": 1, "far": 1, "desperately": 1}, "would": {"draw": 1, "be": 1, "have": 1, "pre-empt": 1}, "draw": {"regulatory": 1, "a": 1}, "regulatory": {"scrutiny.": 1}, "scrutiny.": {"230": 1}, "230": {"$END$": 1}, "$END$": {}, "President": {"Trump": 2}, "Trump": {"said": 1, "has": 1}, "said": {"he": 2}, "he": {"had": 1, "trumpets": 1, "stepped": 1, "begins": 1}, "had": {"no": 1, "huge": 1, "failed": 1, "received": 1}, "no": {"plans": 1, "sign": 1}, "plans": {"to": 1}, "fire": {"Deputy": 1}, "Deputy": {"Attorney": 1}, "Attorney": {"General": 1}, "General": {"Rod": 1}, "Rod": {"Rosenstein,": 1}, "Rosenstein,": {"giving": 1}, "giving": {"a": 1}, "a": {"vote": 1, "rapid": 1, "case": 1, "competitive": 1, "setback": 1, "wave": 1, "surge": 1, "report": 1, "U.N.-led": 1, "man": 2, "tough": 1, "million": 1, "rise": 1, "new": 1, "number": 1, "brief": 2, "troubling": 1, "knife": 1, "guide": 1, "constitutional": 1, "woman.": 1, "three-week": 1, "challenging": 1, "deal": 1, "better": 1, "collision": 1, "stretch": 1, "stop": 1, "long": 1, "defining": 1, "runoff": 1, "Brazilian": 1, "box": 1, "look": 1}, "vote": {"of": 1}, "confidence": {"to": 1}, "No.": {"2": 1}, "2": {"Justice": 1, "pedestrians": 1}, "Justice": {"Department": 1}, "Department": {"official": 1}, "official": {"after": 1, "called": 1}, "after": {"his": 2, "a": 2}, "his": {"future": 1, "Chinese": 1, "skeptical": 1, "disappearance": 1, "positions.": 1, "evangelical": 1, "lifetime": 1}, "future": {"was": 1, "cooperation": 1}, "was": {"called": 1, "expected": 1, "closing,": 1, "shutting": 1, "shared": 1, "driven": 1, "killed": 1}, "called": {"into": 1, "the": 1}, "into": {"question": 1, "three": 1}, "question": {"last": 1}, "last": {"month.": 1, "month,": 1, "time\"": 1}, "month.": {"94": 1, "$END$": 1}, "94": {"$END$": 1}, "Hurricane": {"Michael": 1}, "Michael": {"formed": 1}, "formed": {"off": 1}, "off": {"the": 1, "seeking": 1, "a": 1}, "coast": {"of": 1}, "Cuba": {"and": 1}, "and": {"gathered": 1, "switching": 1, "developing-world": 1, "the": 3, "touch": 1, "joined": 1, "rising": 1, "Paul": 1, "wreckage": 1, "tsunami.": 1, "Uzbekistan": 1, "was": 1, "minorities.": 1, "law": 1, "an": 1, "a": 2, "acquisitions": 1, "more.": 1, "how": 1, "improvements.": 1, "poverty": 1, "instead": 1, "resilience": 1, "California": 1, "state": 1, "2": 1, "avert": 1, "put": 1, "their": 1, "power,": 1, "tech": 1, "casinos": 1, "more": 1, "according": 1, "same-sex": 1}, "gathered": {"strength": 1}, "strength": {"as": 1}, "as": {"it": 2, "CEO": 1, "directors.": 1, "a": 1, "its": 1, "challenges": 1, "finance": 1, "he": 2, "between": 1}, "steamed": {"toward": 1}, "toward": {"the": 1}, "Florida": {"Panhandle,": 1, "Panhandle.": 1}, "Panhandle,": {"where": 1}, "where": {"it": 1, "thousands": 1, "Interpol": 1, "the": 1}, "expected": {"to": 2}, "strike": {"by": 1}, "by": {"Wednesday.": 1, "Americans": 1, "a": 1, "religious": 1, "the": 1, "2035.": 1}, "Wednesday.": {"$END$": 1}, "GE\u2019s": {"choice": 1}, "choice": {"to": 1}, "name": {"board": 1}, "board": {"member": 1, "members.": 1}, "member": {"Larry": 1}, "Larry": {"Culp": 1}, "Culp": {"as": 1}, "CEO": {"has": 1}, "has": {"led": 1, "been": 2, "appointed": 1, "boosted": 1, "had": 1, "asked": 1, "begun": 1}, "led": {"some": 1}, "some": {"executives": 1, "Chinese": 1, "apps": 1, "key": 1}, "executives": {"to": 1, "as": 1}, "wonder": {"whether": 1}, "whether": {"they": 1}, "they": {"would": 1, "draw": 1}, "be": {"better": 1, "exported": 1, "missing": 1, "a": 1}, "better": {"off": 1, "relations": 1, "life.": 1}, "seeking": {"out": 1}, "out": {"long-retired": 1, "a": 1, "that": 1}, "long-retired": {"executives": 1}, "directors.": {"$END$": 1}, "U.S.": {"Secretary": 1, "imports,": 1, "dollar": 1, "bond": 1}, "Secretary": {"of": 1}, "State": {"Mike": 1}, "Mike": {"Pompeo": 1}, "Pompeo": {"exchanged": 1}, "exchanged": {"testy": 1}, "testy": {"words": 1}, "words": {"with": 1}, "with": {"his": 1, "CEOs": 1, "index-fund": 1, "fentanyl": 1, "our": 1, "new": 1, "insomnia": 1, "regular": 1}, "Chinese": {"counterpart": 1, "exporters": 1, "authorities": 1, "youth": 1, "figured": 1}, "counterpart": {"in": 1}, "Beijing": {"as": 1}, "rapid": {"deterioration": 1}, "deterioration": {"of": 1}, "bilateral": {"ties": 1}, "ties": {"threatens": 1}, "threatens": {"to": 1}, "jeopardize": {"future": 1}, "cooperation": {"over": 1}, "over": {"North": 1, "the": 1}, "North": {"Korea.": 1}, "Korea.": {"118": 1, "$END$": 1}, "118": {"$END$": 1}, "There": {"are": 1}, "are": {"thousands": 1, "ducking": 1, "needed": 1, "currently": 1, "believed": 1, "raising": 1, "also": 1, "investigating": 1, "turning": 1}, "individual": {"codes": 1}, "codes": {"to": 1}, "identify": {"goods": 1}, "goods": {"the": 1}, "imports,": {"and": 1}, "switching": {"them": 1}, "them": {"around": 1, "both": 1, "fall": 1, "\"baseless.\"": 1}, "around": {"is": 1, "it,": 1}, "is": {"an": 1, "a": 2, "softening": 1, "premature": 1, "no": 1, "setting": 1, "in": 1, "based": 1, "the": 2, "simply": 1, "still": 1, "one": 1}, "an": {"increasingly": 1, "investigation": 1, "accusation": 1, "increase": 1, "Oklahoma": 1, "estimated": 1, "active": 1, "international": 1, "outright": 1}, "increasingly": {"popular": 1}, "popular": {"way": 1}, "way": {"some": 1}, "exporters": {"are": 1}, "ducking": {"proliferating": 1}, "proliferating": {"American": 1}, "American": {"tariffs,": 1}, "tariffs,": {"say": 1}, "say": {"trade": 1, "authoritarian": 1, "only": 1}, "trade": {"professionals.": 1}, "professionals.": {"The": 1}, "plywood": {"industry": 1}, "industry": {"is": 1, "on": 1}, "case": {"in": 1}, "point.": {"158": 1}, "158": {"$END$": 1}, "Elliott": {"Management,": 1}, "Management,": {"known": 1}, "known": {"for": 1}, "for": {"its": 1, "vehicles": 1, "their": 1, "four": 1, "research": 1, "global": 1, "bodies": 1, "mergers": 1, "College:": 1, "young": 1, "dangerous": 1, "many": 1, "10": 1, "China,\"": 1}, "its": {"brawls": 1, "image.": 1, "lead": 1, "stake": 1, "remote": 1, "jobs": 1}, "brawls": {"with": 1}, "CEOs": {"and": 1}, "developing-world": {"governments,": 1}, "governments,": {"is": 1}, "softening": {"its": 1}, "image.": {"As": 1}, "As": {"the": 2}, "shareholder-activism": {"landscape": 1}, "landscape": {"evolves,": 1}, "evolves,": {"the": 1}, "hedge": {"fund": 2}, "fund": {"has": 1, "D.E.": 1, "to": 1}, "been": {"cultivating": 1, "registered,": 1, "slow,": 1}, "cultivating": {"better": 1}, "relations": {"with": 1}, "index-fund": {"managers": 1}, "managers": {"and": 1}, "companies": {"it": 1}, "targets.": {"$END$": 1}, "German": {"prosecutors": 1}, "prosecutors": {"have": 1}, "have": {"launched": 1, "rallied": 1, "taken": 1, "used": 1, "the": 2, "been": 1, "defined": 1, "put": 1, "long": 1, "denied": 1}, "launched": {"an": 1}, "investigation": {"into": 1}, "three": {"employees": 1}, "employees": {"of": 1}, "Volkswagen\u2019s": {"luxury": 1}, "luxury": {"car": 1}, "car": {"unit": 1}, "unit": {"Audi": 1}, "Audi": {"suspected": 1}, "suspected": {"of": 1}, "falsifying": {"documents": 1}, "documents": {"to": 1}, "obtain": {"roadworthiness": 1}, "roadworthiness": {"certifications": 1}, "certifications": {"needed": 1}, "needed": {"for": 1, "to": 1}, "vehicles": {"to": 1}, "exported": {"to": 1}, "South": {"Korea.": 1}, "two": {"voice-controlled": 1, "strangers": 1}, "voice-controlled": {"tabletop": 1}, "tabletop": {"systems": 1}, "systems": {"feature": 1}, "feature": {"cameras,": 1}, "cameras,": {"microphones": 1}, "microphones": {"and": 1}, "touch": {"screens\u2014and": 1, "with": 1}, "screens\u2014and": {"Amazon\u2019s": 1}, "Amazon\u2019s": {"Alexa.": 1}, "Alexa.": {"$END$": 1}, "Ford": {"Motor": 1}, "Motor": {"has": 1}, "appointed": {"Omnicom": 1}, "Omnicom": {"Group\u2019s": 1}, "Group\u2019s": {"BBDO": 1}, "BBDO": {"as": 1}, "lead": {"creative": 1}, "creative": {"agency": 1}, "agency": {"after": 1}, "competitive": {"review,": 1}, "review,": {"dealing": 1}, "dealing": {"a": 1}, "setback": {"to": 1}, "WPP.": {"$END$": 1}, "Hedge": {"fund": 1}, "D.E.": {"Shaw": 1}, "Shaw": {"has": 1}, "boosted": {"its": 1}, "stake": {"in": 1}, "Bunge": {"and": 1}, "joined": {"Continental": 1}, "Continental": {"Grain": 1}, "Grain": {"in": 1}, "pushing": {"the": 1}, "grain": {"trader": 1}, "trader": {"to": 1}, "make": {"operational": 1, "the": 1}, "operational": {"improvements": 1}, "improvements": {"or": 1}, "or": {"add": 1, "next,": 1, "planning": 1, "brain": 1}, "add": {"board": 1}, "members.": {"$END$": 1}, "Ensco-Rowan": {"merger": 1}, "merger": {"makes": 1}, "makes": {"sense,": 1}, "sense,": {"but": 1}, "but": {"the": 1, "Federal": 1, "religious": 1, "\"it's": 1}, "rally": {"in": 1}, "their": {"shares": 1, "rigs": 1, "excavation": 1}, "shares": {"so": 1}, "far": {"this": 1, "beyond": 1}, "year": {"is": 1, "or": 1, "Chinese": 1}, "premature": {"because": 1}, "there": {"is": 2}, "sign": {"of": 1}, "improving": {"rates": 1}, "rates": {"for": 1}, "rigs": {"this": 1}, "next,": {"despite": 1}, "despite": {"higher": 1}, "higher": {"crude": 1}, "crude": {"prices.": 1}, "prices.": {"$END$": 1}, "A": {"hot": 1, "strong": 1, "scientific": 1}, "hot": {"streak": 1}, "streak": {"in": 1}, "oil": {"market": 1, "options.": 1}, "market": {"is": 1, "for": 1}, "setting": {"off": 1}, "wave": {"of": 1}, "bets": {"on": 1}, "on": {"how": 2, "Monday": 1, "innovation,": 1, "the": 3, "grandparent-funded": 1, "a": 1, "his": 1, "maps:": 1}, "how": {"high": 1, "to": 2}, "high": {"prices": 1}, "prices": {"can": 1, "have": 1}, "can": {"go.": 1, "kill": 1, "help": 1, "achieve": 1}, "go.": {"Crude": 1}, "Crude": {"prices": 1}, "rallied": {"for": 1}, "four": {"weeks,": 1}, "weeks,": {"prompting": 1}, "prompting": {"a": 1}, "surge": {"in": 1}, "trading": {"of": 1}, "options.": {"$END$": 1}, "Many": {"developing": 1}, "developing": {"nations": 1}, "nations": {"have": 1, "that": 1}, "taken": {"steps": 1, "the": 1}, "steps": {"to": 1}, "limit": {"fallout": 1}, "fallout": {"from": 1}, "from": {"recent": 1, "a": 1, "September\u2019s": 1, "August,": 1, "her": 1, "warming": 1, "taking": 1}, "recent": {"U.S.": 1}, "dollar": {"strength,": 1}, "strength,": {"but": 1}, "Federal": {"Reserve": 1}, "Reserve": {"rate": 1}, "rate": {"hikes": 1}, "hikes": {"and": 1}, "rising": {"U.S.": 1}, "bond": {"yields": 1}, "yields": {"loom": 1}, "loom": {"as": 1}, "challenges": {"as": 1}, "finance": {"ministers": 1}, "ministers": {"meet": 1}, "meet": {"this": 1, "the": 1}, "week.": {"$END$": 2}, "New": {"York-based": 1, "York": 1}, "York-based": {"Tourbillon": 1}, "Tourbillon": {"Capital": 1}, "Capital": {"Partners": 1}, "Partners": {"on": 1}, "Monday": {"told": 1, "morning;": 1}, "told": {"investors": 1, "journalists": 1, "reporters": 1}, "investors": {"it": 1}, "closing,": {"marking": 1}, "marking": {"at": 1}, "at": {"least": 1, "some": 1, "the": 2, "1,763,": 1}, "least": {"the": 1}, "third": {"hedge": 1}, "announce": {"it": 1}, "shutting": {"down": 1}, "down": {"this": 1, "amid": 1}, "Rapid,": {"far-reaching": 1}, "far-reaching": {"changes": 1}, "changes": {"to": 1}, "almost": {"every": 1}, "every": {"facet": 1}, "facet": {"of": 1}, "society": {"are": 1}, "avoid": {"catastrophic": 1, "war,": 1}, "catastrophic": {"climate": 1}, "climate": {"change,": 1, "change": 1, "from": 1}, "change,": {"reforms": 1}, "reforms": {"far": 1}, "beyond": {"anything": 1}, "anything": {"governments": 1}, "governments": {"are": 1}, "currently": {"either": 1}, "either": {"doing": 1}, "planning": {"to": 1}, "do,": {"according": 1}, "according": {"to": 2}, "report": {"from": 1, "indicates.": 1}, "U.N.-led": {"scientific": 1}, "scientific": {"panel.": 1, "panel,": 1}, "panel.": {"644": 1}, "644": {"$END$": 1}, "Nobel": {"Prize": 1}, "Prize": {"in": 1}, "Economic": {"Sciences": 1}, "Sciences": {"was": 1}, "shared": {"by": 1}, "Americans": {"William": 1}, "William": {"D.": 1}, "D.": {"Nordhaus": 1}, "Nordhaus": {"and": 1}, "Paul": {"M.": 1}, "M.": {"Romer,": 1}, "Romer,": {"for": 1}, "research": {"on": 1}, "innovation,": {"climate": 1}, "change": {"and": 1}, "economy": {"that": 1, "cut": 1, "and": 1}, "that": {"has": 1, "claimed": 1, "can": 2, "she": 1, "like": 1, "would": 2, "there": 1, "occurred": 1, "the": 1, "box": 1, "Khashoggi": 1, "technology": 1, "already": 1}, "huge": {"implications": 1}, "implications": {"for": 1}, "global": {"policy": 1, "climate": 1}, "policy": {"making.": 1}, "making.": {"443": 1}, "443": {"$END$": 1}, "Indonesia": {"will": 1}, "will": {"halt": 1, "have": 1}, "halt": {"the": 1}, "search": {"for": 1, "of": 1}, "bodies": {"this": 1}, "week": {"where": 1}, "people": {"are": 1, "she": 1, "to": 1, "who": 1}, "believed": {"to": 1}, "missing": {"in": 1}, "mountains": {"of": 1}, "mud": {"and": 1}, "wreckage": {"from": 1}, "September\u2019s": {"devastating": 1}, "devastating": {"earthquake": 1}, "earthquake": {"and": 1}, "tsunami.": {"$END$": 1}, "Human": {"rights": 1}, "rights": {"advocates": 1}, "advocates": {"say": 1}, "authoritarian": {"regimes,": 1}, "regimes,": {"including": 1}, "including": {"China,": 1, "an": 1, "classes": 1}, "China,": {"Russia,": 1}, "Russia,": {"Turkey": 1}, "Turkey": {"and": 1}, "Uzbekistan": {"have": 1}, "used": {"Interpol": 1}, "Interpol": {"to": 1, "of": 1, "said": 1, "is": 1}, "pursue": {"political": 1}, "political": {"targets,": 1, "parodies": 1}, "targets,": {"an": 1}, "accusation": {"the": 1}, "organization": {"denies.": 1}, "denies.": {"$END$": 1}, "limousine": {"involved": 1, "blew": 1}, "involved": {"in": 1}, "upstate": {"New": 1}, "York": {"crash": 1}, "crash": {"that": 1}, "claimed": {"20": 1}, "20": {"lives": 1}, "lives": {"had": 1}, "failed": {"inspection": 1}, "inspection": {"in": 1}, "September": {"and": 1}, "driven": {"by": 1}, "man": {"who": 1, "and": 1}, "who": {"didn\u2019t": 1, "leave": 1}, "required": {"license,": 1}, "license,": {"Gov.": 1}, "Gov.": {"Andrew": 1}, "Andrew": {"Cuomo": 1}, "Cuomo": {"said.": 1}, "said.": {"50": 1, "An": 1}, "50": {"$END$": 1}, "Rep.": {"Erik": 1}, "Erik": {"Paulsen,": 1}, "Paulsen,": {"one": 1}, "one": {"of": 2, "China": 1, "estimate,": 1}, "writers": {"of": 1}, "big": {"GOP": 1}, "GOP": {"tax": 1}, "tax": {"cut,": 1}, "cut,": {"is": 1}, "tough": {"re-election": 1}, "re-election": {"fight": 1}, "fight": {"as": 1}, "trumpets": {"the": 1}, "measure": {"to": 1}, "skeptical": {"Minnesota": 1}, "Minnesota": {"district.": 1}, "district.": {"59": 1}, "59": {"$END$": 1}, "Since": {"Georgians": 1}, "Georgians": {"went": 1}, "went": {"to": 1}, "polls": {"in": 1}, "2016,": {"more": 1}, "more": {"than": 2, "and": 1, "to": 1}, "than": {"half": 1, "1.5": 1, "the": 1}, "half": {"a": 1}, "million": {"voters": 1}, "voters": {"have": 1, "rejected": 1}, "registered,": {"including": 1}, "increase": {"in": 1}, "ranks": {"of": 1}, "women": {"and": 1}, "minorities.": {"55": 1}, "55": {"$END$": 1}, "Drug": {"makers": 1}, "makers": {"and": 1}, "law": {"enforcement": 1}, "enforcement": {"struggle": 1}, "struggle": {"to": 1}, "stop": {"online": 1, "Democrats": 1, "sign.": 1}, "online": {"sales": 1}, "sales": {"of": 1}, "counterfeit": {"versions": 1}, "versions": {"of": 1}, "medications": {"like": 1}, "like": {"Xanax": 1, "most": 1}, "Xanax": {"laced": 1}, "laced": {"with": 1}, "fentanyl": {"that": 1}, "kill": {"unsuspecting": 1}, "unsuspecting": {"users.": 1}, "users.": {"$END$": 1}, "author\u2019s": {"new": 1}, "new": {"book": 1, "report": 1, "sex-abuse": 1, "deal": 1, "data": 1}, "book": {"follows": 1}, "follows": {"two": 1}, "strangers": {"whose": 1}, "whose": {"paths": 1}, "paths": {"cross\u2014a": 1}, "cross\u2014a": {"street-smart": 1}, "street-smart": {"mob": 1}, "mob": {"operator": 1}, "operator": {"and": 1}, "Oklahoma": {"mother\u2014after": 1}, "mother\u2014after": {"JFK\u2019s": 1}, "JFK\u2019s": {"assassination": 1}, "assassination": {"sets": 1}, "sets": {"them": 1}, "both": {"on": 1, "same-sex": 1}, "run.": {"$END$": 1}, "Employers": {"across": 1}, "across": {"the": 1}, "cut": {"an": 1}, "estimated": {"90,000": 1}, "90,000": {"technology": 1}, "technology": {"jobs": 1, "is": 2}, "jobs": {"last": 1, "to": 1}, "month,": {"reversing": 1}, "reversing": {"gains": 1}, "gains": {"from": 1}, "August,": {"CompTIA": 1}, "CompTIA": {"reports.": 1}, "reports.": {"$END$": 1}, "strong": {"domestic": 1}, "domestic": {"economy": 1}, "rise": {"in": 1}, "investor": {"activism": 1}, "activism": {"could": 1}, "could": {"herald": 1, "lose": 1}, "herald": {"an": 1}, "active": {"market": 1}, "mergers": {"and": 1}, "acquisitions": {"in": 1}, "coming": {"year,": 1}, "year,": {"a": 1}, "indicates.": {"Meanwhile,": 1}, "Meanwhile,": {"cross-sector": 1}, "cross-sector": {"suitors": 1}, "suitors": {"are": 1}, "raising": {"the": 1}, "stakes.": {"$END$": 1}, "authorities": {"accused": 1}, "accused": {"Meng": 1}, "Meng": {"Hongwei,": 1, "Hongwei's": 1}, "Hongwei,": {"the": 1}, "head": {"of": 1}, "bribery,": {"days": 1}, "days": {"after": 1}, "disappearance": {"caused": 1}, "caused": {"an": 1}, "international": {"scandal.": 1}, "scandal.": {"Interpol": 1}, "stepped": {"down": 1}, "amid": {"the": 1}, "accusations.": {"$END$": 1}, "Saving": {"for": 1}, "College:": {"We": 1}, "We": {"also": 1}, "also": {"answer": 1, "getting": 1}, "answer": {"readers\u2019": 1}, "readers\u2019": {"questions": 1}, "questions": {"on": 1}, "grandparent-funded": {"529": 1}, "529": {"plans.": 1}, "plans.": {"$END$": 1}, "October": {"8,": 11, "7,": 12, "6,": 1}, "8,": {"2018": 11}, "2018": {"\u2022": 24}, "\u2022": {"The": 4, "Meng": 1, "Alzheimer's": 1, "In": 2, "As": 1, "A": 1, "People": 1, "President": 1, "Though": 1, "National": 1, "\"Together": 1, "Each": 1, "Here's": 1, "Because": 1, "Turkish": 1, "Disaster": 1, "\"The": 1, "Republican": 1, "Hotels": 1, "Romania": 1}, "storm": {"reached": 1}, "reached": {"hurricane": 1}, "hurricane": {"status": 1}, "status": {"Monday": 1}, "morning;": {"it's": 1}, "it's": {"expected": 1, "moving": 1, "trying": 1}, "strengthen": {"rapidly": 1}, "rapidly": {"over": 1}, "next": {"24": 1}, "24": {"hours": 1}, "hours": {"as": 1}, "heads": {"north": 1}, "north": {"towards": 1}, "towards": {"the": 1}, "Panhandle.": {"$END$": 1}, "newly": {"minted": 1}, "minted": {"Supreme": 1}, "Supreme": {"Court": 2}, "Court": {"justice": 1, "confirmation.": 1}, "justice": {"will": 1}, "opportunity": {"to": 1}, "weigh": {"in": 1}, "number": {"of": 1}, "lightning-rod": {"topics:": 1}, "topics:": {"abortion,": 1}, "abortion,": {"guns,": 1}, "guns,": {"executive": 1}, "executive": {"power": 1}, "power": {"and": 1}, "more.": {"Here's": 1}, "Here's": {"a": 4}, "brief": {"primer": 1, "look": 1}, "primer": {"on": 1}, "positions.": {"$END$": 1}, "Hongwei's": {"wife": 1}, "wife": {"told": 1}, "journalists": {"in": 1}, "Lyon": {"\u2014": 1}, "\u2014": {"where": 1, "that": 1, "the": 1, "reducing": 1, "and": 1}, "based": {"\u2014": 1}, "she": {"had": 1, "gets": 1}, "received": {"a": 1}, "troubling": {"text": 1}, "text": {"message": 1}, "message": {"from": 1}, "her": {"husband's": 1}, "husband's": {"phone:": 1}, "phone:": {"a": 1}, "knife": {"emoji.": 1}, "emoji.": {"China": 1}, "China": {"says": 1, "and": 1}, "says": {"he's": 1, "that": 1, "work": 1, "one": 1}, "he's": {"under": 1}, "under": {"investigation.": 1}, "investigation.": {"$END$": 1}, "At": {"NPR,": 1}, "NPR,": {"we": 1}, "we": {"welcome": 1, "can": 1}, "welcome": {"your": 1}, "your": {"news": 1}, "news": {"tips.": 1}, "tips.": {"Here's": 1}, "guide": {"to": 1}, "getting": {"in": 1, "people": 1}, "our": {"newsroom": 1}, "newsroom": {"and": 1}, "share": {"sensitive": 1}, "sensitive": {"information.": 1}, "information.": {"$END$": 1}, "Alzheimer's": {"prevention": 1}, "prevention": {"specialist": 1}, "specialist": {"Jessica": 1}, "Jessica": {"Langbaum": 1}, "Langbaum": {"says": 1}, "most": {"working": 1}, "working": {"people": 1}, "gets": {"plenty": 1}, "plenty": {"of": 1}, "mental": {"exercise": 1}, "exercise": {"without": 1}, "without": {"playing": 1}, "playing": {"crossword": 1}, "crossword": {"puzzles": 1}, "puzzles": {"or": 1}, "brain": {"games.": 1}, "games.": {"She": 1}, "She": {"says": 1}, "work": {"is": 1}, "key.": {"$END$": 1}, "In": {"failing": 1, "a": 1}, "failing": {"to": 1}, "minimum": {"turnout,": 1}, "turnout,": {"voters": 1}, "rejected": {"a": 1}, "constitutional": {"amendment": 1}, "amendment": {"championed": 1}, "championed": {"by": 1}, "religious": {"groups": 1, "progressives": 1}, "groups": {"that": 1}, "defined": {"marriage": 1}, "marriage": {"as": 1, "and": 1}, "between": {"a": 1}, "woman.": {"$END$": 1}, "Catholic": {"Church": 1}, "Church": {"deals": 1, "relevant": 1}, "deals": {"with": 1}, "sex-abuse": {"revelations,": 1}, "revelations,": {"the": 1}, "pope": {"opened": 1}, "opened": {"a": 1, "deep": 1}, "three-week": {"gathering": 1}, "gathering": {"of": 1}, "bishops": {"in": 1}, "Rome": {"Saturday": 1}, "Saturday": {"on": 1, "in": 1, "Night": 1}, "relevant": {"for": 1}, "young": {"people.": 1}, "people.": {"$END$": 1}, "panel,": {"convened": 1}, "convened": {"by": 1}, "U.N.,": {"lays": 1}, "lays": {"out": 1}, "challenging": {"path": 1}, "path": {"to": 1}, "keep": {"the": 1}, "warming": {"more": 1}, "1.5": {"degrees": 1}, "degrees": {"Celsius": 1}, "Celsius": {"\u2014": 1}, "red": {"line": 1}, "line": {"for": 1}, "dangerous": {"consequences.": 1}, "consequences.": {"$END$": 1}, "deal": {"to": 1, "\u2014": 1}, "replace": {"NAFTA": 1}, "NAFTA": {"includes": 1}, "includes": {"modernizations": 1}, "modernizations": {"and": 1}, "improvements.": {"But": 1}, "But": {"the": 1, "scientists": 1}, "biggest": {"benefit,": 1}, "benefit,": {"for": 1}, "many": {"sectors,": 1}, "sectors,": {"is": 1}, "simply": {"that": 1}, "reducing": {"the": 1}, "uncertainty": {"of": 1}, "previous": {"months.": 1}, "months.": {"$END$": 1}, "People": {"struggling": 1}, "struggling": {"with": 1}, "insomnia": {"often": 1}, "often": {"turn": 1}, "turn": {"to": 1}, "apps": {"to": 1, "use": 1}, "help": {"them": 1, "address": 1, "stop": 1}, "fall": {"asleep.": 1}, "asleep.": {"But": 1}, "scientists": {"say": 1}, "only": {"some": 1}, "use": {"proven": 1}, "proven": {"methods": 1}, "methods": {"that": 1}, "address": {"the": 1}, "underlying": {"causes": 1}, "causes": {"of": 1}, "sleeplessness.": {"$END$": 1}, "asked": {"his": 1}, "evangelical": {"supporters": 1}, "supporters": {"to": 1}, "Democrats": {"from": 1}, "taking": {"control": 1}, "control": {"of": 1}, "Congress,": {"but": 1}, "progressives": {"are": 1}, "polls.": {"$END$": 1}, "7,": {"2018": 12}, "photos": {"avoid": 1}, "war,": {"destruction": 1}, "destruction": {"and": 1}, "poverty": {"\u2014": 1}, "instead": {"focus": 1}, "focus": {"on": 1}, "beauty": {"and": 1}, "resilience": {"of": 1}, "leave": {"home": 1}, "home": {"in": 1}, "life.": {"$END$": 1}, "Though": {"new": 1}, "privacy": {"laws": 1}, "laws": {"in": 1}, "Europe": {"and": 1}, "California": {"have": 1}, "put": {"the": 2, "that": 1}, "tech": {"industry": 1, "watcher.": 1}, "defensive,": {"it's": 1}, "moving": {"to": 1}, "craft": {"federal": 1}, "federal": {"legislation": 1}, "legislation": {"that": 1}, "pre-empt": {"state": 1}, "state": {"laws.": 1, "officials": 1, "said.": 1}, "laws.": {"$END$": 1}, "National": {"and": 1}, "officials": {"are": 1, "told": 1, "have": 1, "put": 1}, "investigating": {"a": 1}, "collision": {"that": 1}, "occurred": {"Saturday": 1}, "Schoharie,": {"after": 1}, "stretch": {"limousine": 1}, "blew": {"past": 1}, "sign.": {"The": 1}, "driver,": {"all": 1}, "all": {"the": 1}, "passengers": {"and": 1}, "pedestrians": {"died.": 1}, "died.": {"$END$": 1}, "\"Together": {"we": 1}, "achieve": {"the": 1}, "outcome": {"that": 1}, "world": {"so": 1}, "desperately": {"needs,\"": 1}, "needs,\"": {"the": 1}, "secretary": {"of": 1}, "An": {"official": 1}, "meeting": {"\"better": 1}, "\"better": {"than": 1}, "time\"": {"but": 1}, "\"it's": {"going": 1}, "going": {"to": 1}, "long": {"haul.\"": 1, "taken": 1}, "haul.\"": {"$END$": 1}, "defining": {"presidential": 1}, "presidential": {"election": 1}, "election": {"that's": 1}, "that's": {"opened": 1}, "deep": {"divisions,": 1}, "divisions,": {"Jair": 1}, "Jair": {"Bolsonaro": 1}, "Bolsonaro": {"fell": 1}, "fell": {"just": 1}, "just": {"short": 1}, "short": {"of": 1}, "claiming": {"an": 1}, "outright": {"victory,": 1}, "victory,": {"and": 1}, "avert": {"a": 1}, "runoff": {"against": 1}, "against": {"leftist": 1}, "leftist": {"rival": 1}, "rival": {"Fernando": 1}, "Fernando": {"Haddad.": 1}, "Haddad.": {"$END$": 1}, "Each": {"year": 1}, "youth": {"teams": 1}, "teams": {"send": 1}, "send": {"members": 1}, "members": {"to": 1}, "Brazilian": {"academy": 1}, "academy": {"for": 1}, "10": {"months": 1}, "months": {"of": 1}, "soccer": {"coupled": 1}, "coupled": {"with": 1}, "regular": {"school": 1}, "school": {"lessons,": 1}, "lessons,": {"including": 1}, "classes": {"in": 1}, "Portuguese.": {"$END$": 1}, "look": {"at": 2}, "key": {"information": 1, "to": 1}, "information": {"about": 1}, "about": {"Kavanaugh": 1}, "Kavanaugh": {"as": 1}, "begins": {"his": 1}, "lifetime": {"appointment": 1}, "appointment": {"to": 1}, "nation's": {"highest": 1}, "highest": {"court.": 1}, "court.": {"$END$": 1}, "Because": {"of": 1}, "remote": {"location,": 1}, "location,": {"cartographers": 1}, "cartographers": {"have": 1}, "same": {"approach": 1}, "approach": {"to": 1}, "representing": {"the": 1}, "Scottish": {"archipelago": 1}, "archipelago": {"on": 1}, "maps:": {"they": 1}, "box": {"around": 1, "wherever": 1}, "it,": {"and": 1}, "wherever": {"it": 1}, "fits.": {"$END$": 1}, "Turkish": {"officials": 1}, "reporters": {"that": 1}, "Khashoggi": {"was": 1}, "killed": {"at": 1}, "Saudi": {"embassy": 1, "officials": 1}, "embassy": {"in": 1}, "Istanbul.": {"Saudi": 1}, "denied": {"the": 1}, "allegations,": {"calling": 1}, "calling": {"them": 1}, "\"baseless.\"": {"$END$": 1}, "Disaster": {"management": 1}, "management": {"officials": 1}, "death": {"toll": 1}, "toll": {"at": 1}, "1,763,": {"and": 1}, "excavation": {"has": 1}, "slow,": {"especially": 1}, "especially": {"in": 1}, "areas": {"where": 1}, "quake": {"buried": 1}, "buried": {"whole": 1}, "whole": {"blocks": 1}, "blocks": {"of": 1}, "houses.": {"International": 1}, "International": {"aid": 1}, "aid": {"has": 1}, "begun": {"arriving.": 1}, "arriving.": {"$END$": 1}, "\"The": {"Chinese": 1}, "figured": {"out": 1}, "wealth": {"and": 1}, "power,": {"and": 1}, "source": {"of": 1}, "still": {"the": 1}, "West": {"for": 1}, "China,\"": {"says": 1}, "watcher.": {"$END$": 1}, "Republican": {"senators": 1}, "senators": {"were": 1}, "were": {"in": 1}, "full": {"party": 1}, "party": {"mode": 1}, "mode": {"in": 1}, "Night": {"Live's": 1}, "Live's": {"cold": 1}, "cold": {"open,": 1}, "open,": {"the": 1}, "day": {"of": 1}, "Brett": {"Kavanaugh's": 1}, "Kavanaugh's": {"Supreme": 1}, "confirmation.": {"Here's": 1}, "show's": {"political": 1}, "parodies": {"this": 1}, "Hotels": {"and": 1}, "casinos": {"are": 1}, "turning": {"more": 1}, "technology,": {"and": 1}, "estimate,": {"the": 1}, "city": {"could": 1}, "lose": {"up": 1}, "up": {"to": 1}, "two-thirds": {"of": 1}, "automation": {"by": 1}, "2035.": {"$END$": 1}, "6,": {"2018": 1}, "Romania": {"is": 1}, "several": {"Eastern": 1}, "Eastern": {"European": 1}, "European": {"nations": 1}, "already": {"ban": 1}, "ban": {"both": 1, "it": 1}, "same-sex": {"marriage": 1, "unions": 1}, "unions": {"in": 1}, "civil": {"law.": 1}, "law.": {"Now": 1}, "Now": {"it's": 1}, "trying": {"to": 1}, "constitution.": {"$END$": 1}}