{"$START$": {"U.S.": 1, "Roman": 1, "North": 1, "The": 6, "Firefighters": 1, "From": 1, "AT&T": 1, "Pet": 1, "Oil": 1, "Some": 1, "SoftBank": 1, "Moderna": 1, "Canada\u2019s": 1, "Western": 1, "Delia": 1, "Major": 1, "November": 24, "At": 1}, "U.S.": {"stocks": 1, "have": 1, "voiced": 1, "isn\u2019t": 1, "official": 1, "Supreme": 1, "Senate.": 1}, "stocks": {"tumbled,": 1}, "tumbled,": {"pulling": 1}, "pulling": {"the": 1}, "the": {"Dow": 1, "health": 1, "market.": 1, "nation": 1, "Vatican": 1, "sex-abuse": 1, "church": 1, "U.S.": 2, "electorate": 1, "midterms,": 1, "business,": 1, "company": 1, "Brooklyn": 1, "challenges": 1, "initial": 1, "largest": 1, "country": 1, "first": 2, "journalist": 1, "United": 2, "Crawdads": 1, "resource": 1, "state.": 1, "audio": 1, "fate": 1, "presidency": 1, "nation's": 1, "Voting": 1, "former": 1, "government": 1, "products": 1, "eerie,": 1, "1968": 1, "Shakespearean": 1, "Netherlands,": 1, "Dutch": 1, "grave's": 1, "problem": 1, "sanctions": 1, "penalties.": 1, "Arc": 1, "style": 1, "most": 1, "NRA.": 1, "past": 1, "mass": 1, "gunman.": 1, "Navajo": 1, "plant": 1, "country's": 1, "House": 1, "midterm": 1, "meth": 1, "races": 1}, "Dow": {"Jones": 1}, "Jones": {"Industrial": 1}, "Industrial": {"Average": 1}, "Average": {"down": 1}, "down": {"more": 1, "the": 1}, "more": {"than": 5, "bodies": 1}, "than": {"400": 1, "200": 1, "meals.": 1, "$20": 1, "sitting": 1, "50": 1, "1,000": 1}, "400": {"points,": 1}, "points,": {"as": 1}, "as": {"anxiety": 1, "talks": 1, "\u201cPalantir": 1, "it": 3, "OPEC": 1, "crazy": 1, "many": 1, "4": 1}, "anxiety": {"over": 1}, "over": {"the": 2, "\"hanging": 1}, "health": {"of": 1}, "of": {"technology": 1, "undeclared": 1, "commercial": 1, "brands,": 1, "new": 1, "losses,": 1, "its": 1, "movement.": 1, "government": 1, "crucial": 1, "the": 3, "movement": 1, "performances": 1, "internment": 1, "spousal": 1, "nationalism": 1, "retirements": 1, "his": 1, "at": 1, "technicians": 1, "newly": 1, "votes": 1, "debate,": 1, "taking": 1}, "technology": {"behemoths": 1}, "behemoths": {"rippled": 1}, "rippled": {"across": 1}, "across": {"the": 2}, "market.": {"$END$": 1}, "$END$": {}, "Roman": {"Catholic": 1}, "Catholic": {"bishops": 1}, "bishops": {"from": 1}, "from": {"around": 1, "other": 1, "collapse,": 1, "the": 1, "her": 1, "ethnic": 1, "Paul": 1, "trying": 1, "Breaking": 1}, "around": {"the": 1}, "nation": {"have": 1}, "have": {"been": 1, "stalled,": 1, "big": 1, "claimed": 1, "prompted": 1, "presented": 1, "disappeared": 1}, "been": {"ordered": 1, "run": 1, "fully": 1, "delayed,": 1, "embraced": 1}, "ordered": {"by": 1}, "by": {"the": 1, "Mexican": 1, "Saudi": 1, "Europe\u2019s": 1, "President": 1, "this": 1}, "Vatican": {"not": 1}, "not": {"to": 1, "anti-gun:": 1}, "to": {"take": 1, "address": 1, "win": 1, "remake": 1, "what\u2019s": 1, "stay": 1, "protecting": 1, "milk": 1, "Sazerac": 1, "cut": 1, "buy": 1, "raise": 1, "fuel": 1, "offer": 1, "repatriate": 1, "Bangladesh,": 1, "face": 1, "publicly": 1, "an": 1, "help": 1, "rescue": 1, "hold": 1, "make": 1, "demonstrate": 1, "a": 2, "control": 1, "share,\"": 1, "acknowledge": 1, "cast": 1, "getting": 1, "share": 1, "hit": 1, "HAL": 1, "negotiate": 1, "avoid": 1, "Beto": 1, "Claire": 1, "the": 3, "save": 1, "report": 1, "close": 1, "attract": 1, "count": 1, "say": 1, "find": 1, "protect": 1}, "take": {"any": 1}, "any": {"actions": 1, "overall": 1}, "actions": {"at": 1}, "at": {"their": 1, "least": 2, "market": 1, "home": 1, "grocery": 1, "Princeton": 1, "the": 2}, "their": {"annual": 1, "U.S.-traded": 1, "return": 1, "freedom": 1}, "annual": {"meeting": 1}, "meeting": {"to": 1}, "address": {"the": 1}, "sex-abuse": {"crisis": 1}, "crisis": {"that": 1}, "that": {"has": 2, "have": 1, "his": 1, "Turkish": 1, "the": 1, "offers": 1, "ultimately": 1, "were": 1, "left": 1}, "has": {"rocked": 1, "been": 4, "struck": 1, "updated": 1, "collected": 1, "had": 1, "dropped": 1}, "rocked": {"the": 1}, "church": {"this": 1}, "this": {"year.": 2, "fall,": 1, "country.": 1, "week": 2}, "year.": {"$END$": 2}, "North": {"Korea": 1}, "Korea": {"is": 1}, "is": {"maintaining": 1, "now": 1, "selling": 1, "putting": 1, "slated": 1, "evidence": 1, "being": 1, "better": 1, "implicated": 1, "scheduled": 1, "one": 1, "trying": 1}, "maintaining": {"a": 1}, "a": {"network": 3, "data-analysis": 1, "scrappy": 1, "quarter": 1, "portfolio": 1, "flood": 1, "willingness": 1, "$7": 1, "special": 1, "U.S.": 1, "new": 2, "plan": 1, "chord": 1, "best-seller.": 1, "study": 1, "massive": 1, "long": 1, "guide": 1, "50-year-old": 1, "baby.": 1, "federal": 1, "Connecticut": 1, "speech": 1, "mix": 1, "photo": 1, "gunshot": 1, "good": 1, "team": 1, "person.\"": 1, "major": 1}, "network": {"of": 2, "built": 1}, "undeclared": {"ballistic-missile": 1}, "ballistic-missile": {"operating": 1}, "operating": {"bases": 1}, "bases": {"as": 1}, "talks": {"with": 1}, "with": {"the": 2, "fancier": 1, "Iran": 1, "Reese": 1, "our": 1, "beetle": 1}, "stalled,": {"an": 1}, "an": {"analysis": 1, "IPO,": 1, "end": 1, "audio": 1, "alternative.": 1}, "analysis": {"of": 1}, "commercial": {"satellite": 1}, "satellite": {"images": 1}, "images": {"suggests.": 1}, "suggests.": {"75": 1}, "75": {"$END$": 1}, "The": {"Democratic": 1, "Silicon": 1, "world\u2019s": 1, "U.S.": 2, "former": 1, "weeks-long": 1, "first": 1, "new": 1, "Trump": 1}, "Democratic": {"Party": 1}, "Party": {"managed": 1}, "managed": {"to": 1}, "win": {"broad": 1}, "broad": {"appeal": 1}, "appeal": {"across": 1}, "electorate": {"during": 1}, "during": {"the": 1}, "midterms,": {"which": 1}, "which": {"could": 1, "has": 1}, "could": {"have": 1, "complicate": 1, "face": 1}, "big": {"implications": 1}, "implications": {"for": 1}, "for": {"2020,": 1, "its": 1, "$550": 1, "mainstream": 1, "dogs": 1, "their": 1, "a": 1, "human": 1, "the": 1, "his": 1, "Navajo": 1, "an": 1, "governor": 1}, "2020,": {"Gerald": 1}, "Gerald": {"F.": 1}, "F.": {"Seib": 1}, "Seib": {"writes.": 1}, "writes.": {"98": 1}, "98": {"$END$": 1}, "Silicon": {"Valley": 1}, "Valley": {"unicorn,": 1}, "unicorn,": {"a": 1}, "data-analysis": {"giant": 1}, "giant": {"that\u2019s": 1}, "that\u2019s": {"inching": 1}, "inching": {"toward": 1}, "toward": {"an": 1, "premium": 1}, "IPO,": {"has": 1}, "run": {"like": 1}, "like": {"a": 1, "if": 1}, "scrappy": {"startup,": 1}, "startup,": {"including": 1}, "including": {"lavish": 1, "bringing": 1, "Goldschl\u00e4ger": 1, "the": 1}, "lavish": {"perks.": 1}, "perks.": {"CEO": 1}, "CEO": {"Alex": 1}, "Alex": {"Karp": 1}, "Karp": {"is": 1}, "now": {"under": 1}, "under": {"pressure": 1, "evacuation,": 1}, "pressure": {"to": 1, "on": 1}, "remake": {"the": 1}, "business,": {"including": 1}, "bringing": {"an": 1}, "end": {"to": 1}, "what\u2019s": {"known": 1}, "known": {"inside": 1, "for": 1}, "inside": {"the": 1, "strawberries": 1}, "company": {"as": 1}, "\u201cPalantir": {"Entitlement": 1}, "Entitlement": {"Syndrome.\u201d": 1}, "Syndrome.\u201d": {"$END$": 1}, "Firefighters": {"are": 2}, "are": {"battling": 1, "eating": 1, "selling": 1, "trying": 1, "failing": 1, "racing": 1, "voluntarily": 1, "overt": 1, "not": 1, "anti-bullet": 1, "there,": 1}, "battling": {"two": 1}, "two": {"deadly": 1, "weeks": 1, "areas": 1, "audio": 1}, "deadly": {"California": 1}, "California": {"wildfires": 1}, "wildfires": {"that": 1}, "claimed": {"at": 1}, "least": {"31": 1, "16": 1}, "31": {"lives,": 1}, "lives,": {"left": 1}, "left": {"more": 1, "13": 1}, "200": {"people": 1}, "people": {"missing": 1}, "missing": {"and": 1}, "and": {"a": 2, "few": 1, "advertising,": 1, "Seagram\u2019s": 1, "higher-growth": 1, "cats": 1, "its": 1, "noting": 1, "enough": 1, "clothing": 1, "how": 1, "tighten": 1, "could": 1, "about": 1, "is": 1, "the": 1, "Uighurs": 1, "solutions": 1, "covert": 1, "defeats": 1, "last": 1, "Hopi": 1, "U.S.": 1}, "quarter": {"million": 1}, "million": {"under": 1, "as": 1}, "evacuation,": {"while": 1}, "while": {"unhealthy": 1, "Verizon": 1}, "unhealthy": {"smoke": 1}, "smoke": {"levels": 1}, "levels": {"have": 1}, "prompted": {"warnings": 1}, "warnings": {"to": 1}, "stay": {"indoors.": 1, "healthy": 1}, "indoors.": {"275": 1}, "275": {"$END$": 1}, "From": {"closing": 1}, "closing": {"down": 1}, "Brooklyn": {"Bridge": 1}, "Bridge": {"to": 1}, "protecting": {"jurors,": 1}, "jurors,": {"New": 1}, "New": {"York": 1}, "York": {"City": 1}, "City": {"braces": 1}, "braces": {"for": 1}, "its": {"most": 1, "allies": 1, "Japanese": 1, "nearly": 1, "physical": 1}, "most": {"high-risk": 1, "high-profile": 1}, "high-risk": {"trial": 1}, "trial": {"in": 1}, "in": {"years,": 1, "the": 7, "two": 1, "Paris,": 1, "touch": 1, "jail": 1, "common": 1, "more": 1, "Xinjiang.": 1, "our": 1, "response": 1, "Las": 1, "Thousand": 1, "coffins": 1, "this": 1}, "years,": {"and": 1, "the": 1}, "few": {"defendants": 1}, "defendants": {"have": 1}, "presented": {"the": 1}, "challenges": {"posed": 1}, "posed": {"by": 1}, "Mexican": {"drug": 1}, "drug": {"lord": 1}, "lord": {"Joaqu\u00edn": 1}, "Joaqu\u00edn": {"\u201cEl": 1}, "\u201cEl": {"Chapo\u201d": 1}, "Chapo\u201d": {"Guzm\u00e1n.": 1}, "Guzm\u00e1n.": {"79": 1}, "79": {"$END$": 1}, "AT&T": {"plunges": 1}, "plunges": {"into": 1}, "into": {"programming": 1, "all": 1, "a": 1, "the": 1}, "programming": {"and": 1}, "advertising,": {"while": 1}, "Verizon": {"banks": 1}, "banks": {"on": 1}, "on": {"a": 1, "prices.": 1, "record,": 1, "their": 1, "her": 1, "principles": 1, "what": 1, "would": 1, "your": 1, "the": 2, "Tuesday,": 1}, "built": {"to": 1}, "milk": {"5G": 1}, "5G": {"technology.": 1}, "technology.": {"$END$": 1}, "world\u2019s": {"largest": 1}, "largest": {"liquor": 1, "Biotech": 1}, "liquor": {"maker": 1}, "maker": {"is": 1}, "selling": {"a": 1, "faster": 1}, "portfolio": {"of": 1}, "brands,": {"including": 1}, "Goldschl\u00e4ger": {"and": 1}, "Seagram\u2019s": {"VO": 1}, "VO": {"whiskey,": 1}, "whiskey,": {"to": 1}, "Sazerac": {"for": 1}, "$550": {"million": 1}, "it": {"pivots": 1, "seeks": 1, "sounds.": 1, "a": 1}, "pivots": {"toward": 1}, "premium": {"brands": 1}, "brands": {"and": 1}, "higher-growth": {"products.": 1}, "products.": {"$END$": 1}, "Pet": {"foods": 1}, "foods": {"with": 1}, "fancier": {"ingredients": 1}, "ingredients": {"are": 1}, "eating": {"away": 1}, "away": {"at": 1}, "market": {"share": 1}, "share": {"for": 1, "sensitive": 1}, "mainstream": {"brands.": 1}, "brands.": {"Snacks": 1}, "Snacks": {"for": 1}, "dogs": {"and": 1}, "cats": {"are": 2, "kill": 1}, "faster": {"than": 1}, "meals.": {"And": 1}, "And": {"a": 1}, "flood": {"of": 1}, "new": {"products": 1, "bid": 1, "message?": 1, "studies": 1, "nuclear": 1}, "products": {"is": 2, "off": 1}, "putting": {"pressure": 1}, "prices.": {"$END$": 1}, "Oil": {"prices": 1}, "prices": {"rebounded": 1}, "rebounded": {"Monday": 1}, "Monday": {"after": 1}, "after": {"two": 1, "America": 1, "the": 1, "narrow": 1}, "weeks": {"of": 1}, "losses,": {"as": 1}, "OPEC": {"and": 1}, "allies": {"signaled": 1}, "signaled": {"a": 1}, "willingness": {"to": 1}, "cut": {"production": 1}, "production": {"amid": 1}, "amid": {"surging": 1}, "surging": {"global": 1}, "global": {"supply.": 1}, "supply.": {"$END$": 1}, "Some": {"Chinese": 1}, "Chinese": {"executives": 1}, "executives": {"are": 1}, "trying": {"to": 3}, "buy": {"their": 1}, "U.S.-traded": {"companies": 1}, "companies": {"back": 1, "in": 1}, "back": {"from": 1}, "other": {"shareholders,": 1}, "shareholders,": {"even": 1}, "even": {"though": 1}, "though": {"cooling": 1, "a": 1}, "cooling": {"markets": 1}, "markets": {"at": 1}, "home": {"could": 1}, "complicate": {"relistings.": 1}, "relistings.": {"$END$": 1}, "SoftBank": {"will": 1}, "will": {"seek": 1, "vote": 1, "force": 1, "soon": 1, "begin": 1}, "seek": {"to": 1}, "raise": {"more": 1}, "$20": {"billion": 1}, "billion": {"with": 1, "investment": 1, "valuation": 1, "birds": 1}, "initial": {"public": 1}, "public": {"offering": 1}, "offering": {"of": 1}, "Japanese": {"mobile": 1}, "mobile": {"unit,": 1}, "unit,": {"as": 1}, "seeks": {"funds": 1}, "funds": {"to": 1}, "fuel": {"its": 1}, "nearly": {"$100": 1}, "$100": {"billion": 1}, "investment": {"machine.": 1}, "machine.": {"$END$": 1}, "Moderna": {"is": 1}, "slated": {"to": 1}, "offer": {"the": 1, "unexpected": 1}, "Biotech": {"IPO": 1}, "IPO": {"on": 1}, "record,": {"and": 1}, "$7": {"billion": 1}, "valuation": {"isn\u2019t": 1}, "isn\u2019t": {"as": 1, "concerned": 1}, "crazy": {"as": 1}, "sounds.": {"$END$": 1}, "voiced": {"concern": 1}, "concern": {"about": 1}, "about": {"Myanmar\u2019s": 1, "her": 2}, "Myanmar\u2019s": {"plans": 1}, "plans": {"to": 1, "for": 1}, "repatriate": {"Rohingya": 1}, "Rohingya": {"who": 1}, "who": {"fled": 1, "had": 1, "were": 1}, "fled": {"to": 1}, "Bangladesh,": {"saying": 1}, "saying": {"conditions": 1}, "conditions": {"weren\u2019t": 1}, "weren\u2019t": {"yet": 1}, "yet": {"conducive": 1}, "conducive": {"for": 1}, "return": {"and": 1}, "noting": {"those": 1}, "those": {"who": 1}, "had": {"remained": 1, "listened": 1, "to": 2}, "remained": {"in": 1}, "country": {"continued": 1}, "continued": {"to": 1}, "face": {"severe": 1, "10": 1}, "severe": {"restrictions": 1}, "restrictions": {"on": 1}, "freedom": {"of": 1}, "movement.": {"$END$": 1}, "Canada\u2019s": {"Justin": 1}, "Justin": {"Trudeau": 2}, "Trudeau": {"became": 1, "said": 1}, "became": {"the": 1}, "first": {"leader": 1, "novel,": 1, "Western": 1, "bill": 1, "lady": 1}, "leader": {"to": 2}, "publicly": {"say": 1}, "say": {"that": 1, "is": 1, "six": 1, "Davidson": 1}, "his": {"country\u2019s": 1, "decades": 1, "grandfather's": 1, "own": 1}, "country\u2019s": {"intelligence": 1}, "intelligence": {"officials": 1}, "officials": {"had": 1, "say": 2, "launched": 1}, "listened": {"to": 1}, "audio": {"recording": 1, "recordings.": 1, "clips": 1}, "recording": {"that": 1}, "Turkish": {"officials": 1}, "evidence": {"that": 1}, "journalist": {"Jamal": 1}, "Jamal": {"Khashoggi": 1}, "Khashoggi": {"was": 1}, "was": {"killed": 1, "best": 1, "also": 1, "a": 1}, "killed": {"by": 1}, "Saudi": {"operatives.": 1}, "operatives.": {"$END$": 1}, "concerned": {"by": 1}, "Europe\u2019s": {"plans": 1}, "special": {"purpose": 1}, "purpose": {"vehicle": 1}, "vehicle": {"to": 1}, "help": {"enable": 1}, "enable": {"trade": 1}, "trade": {"with": 1}, "Iran": {"after": 1, "to": 1}, "America": {"reinstated": 1}, "reinstated": {"sanctions,": 1}, "sanctions,": {"a": 1}, "official": {"said.": 1}, "said.": {"$END$": 1}, "Western": {"officials": 1, "leader": 1}, "launched": {"a": 1}, "bid": {"to": 1}, "rescue": {"Libya\u2019s": 1}, "Libya\u2019s": {"troubled": 1}, "troubled": {"peace": 1}, "peace": {"process": 1}, "process": {"from": 1}, "collapse,": {"days": 1}, "days": {"after": 1}, "United": {"Nations": 1, "Nations.": 1}, "Nations": {"officially": 1}, "officially": {"discarded": 1}, "discarded": {"a": 1}, "plan": {"to": 1}, "hold": {"elections": 1}, "elections": {"this": 1}, "Delia": {"Owens": 1}, "Owens": {"spent": 1}, "spent": {"10": 1}, "10": {"years": 2, "years,": 1}, "years": {"on": 1, "in": 1, "of": 1}, "her": {"first": 1, "memoir,": 1, "life": 1, "difficulties": 1}, "novel,": {"\u201cWhere": 1}, "\u201cWhere": {"the": 1}, "Crawdads": {"Sing,\u201d": 1}, "Sing,\u201d": {"which": 1}, "struck": {"a": 1}, "chord": {"with": 1}, "Reese": {"Witherspoon": 1}, "Witherspoon": {"and": 1}, "enough": {"readers": 1}, "readers": {"to": 1}, "make": {"it": 1}, "best-seller.": {"$END$": 1}, "Major": {"companies": 1}, "resource": {"extraction,": 1}, "extraction,": {"agricultural": 1}, "agricultural": {"and": 1}, "clothing": {"industries": 1}, "industries": {"are": 1}, "failing": {"to": 1}, "demonstrate": {"respect": 1}, "respect": {"for": 1}, "human": {"rights,": 1}, "rights,": {"according": 1}, "according": {"to": 1}, "study": {"based": 1, "failed": 1}, "based": {"on": 1}, "principles": {"from": 1}, "Nations.": {"$END$": 1}, "former": {"Microsoft": 1, "first": 1}, "Microsoft": {"chief": 1}, "chief": {"created": 1}, "created": {"a": 1}, "massive": {"database": 1}, "database": {"of": 1}, "government": {"data": 1, "has": 1, "funded": 1}, "data": {"that": 1}, "offers": {"insight": 1}, "insight": {"into": 1}, "all": {"sorts": 1}, "sorts": {"of": 1}, "crucial": {"issues.": 1}, "issues.": {"$END$": 1}, "November": {"12,": 12, "11,": 10, "10,": 2}, "12,": {"2018": 12}, "2018": {"\u2022": 24}, "\u2022": {"Firefighters": 1, "\"Canada": 1, "The": 3, "Earlier": 1, "In": 3, "After": 3, "A": 2, "Rain": 1, "Two": 1, "Thanks": 1, "\"We": 1, "For": 1, "Rare": 1, "Republican": 1, "Outdoor": 1, "Pete": 1, "Machine": 1}, "racing": {"against": 1}, "against": {"wind": 1, "heart": 1}, "wind": {"gusts": 1}, "gusts": {"to": 1}, "control": {"blazes": 1}, "blazes": {"raging": 1}, "raging": {"in": 1}, "areas": {"of": 1}, "state.": {"In": 1}, "In": {"Northern": 1, "two": 1, "a": 1, "the": 1}, "Northern": {"California,": 1}, "California,": {"officials": 1}, "six": {"more": 1}, "bodies": {"were": 1}, "were": {"found.": 1, "repeatedly": 1, "the": 1, "also": 1, "newly": 1, "reported": 1}, "found.": {"$END$": 1, "Egypt": 1}, "\"Canada": {"has": 1}, "fully": {"briefed": 1}, "briefed": {"up": 1}, "up": {"on": 1}, "what": {"Turkey": 1}, "Turkey": {"had": 1}, "share,\"": {"Prime": 1}, "Prime": {"Minister": 1}, "Minister": {"Justin": 1}, "said": {"in": 1}, "Paris,": {"becoming": 1}, "becoming": {"the": 1}, "acknowledge": {"the": 1}, "recordings.": {"$END$": 1}, "weeks-long": {"battle": 1}, "battle": {"over": 1}, "\"hanging": {"chads\"": 1}, "chads\"": {"that": 1}, "ultimately": {"landed": 1}, "landed": {"the": 1}, "fate": {"of": 1}, "presidency": {"in": 1}, "Supreme": {"Court,": 1}, "Court,": {"continues": 1}, "continues": {"to": 1}, "cast": {"a": 1}, "long": {"shadow": 1}, "shadow": {"over": 1}, "nation's": {"political": 1}, "political": {"psyche.": 1}, "psyche.": {"$END$": 1}, "At": {"NPR,": 1}, "NPR,": {"we": 1}, "we": {"welcome": 1, "are": 1}, "welcome": {"your": 1}, "your": {"news": 1, "couch.": 1}, "news": {"tips.": 1}, "tips.": {"Here's": 1}, "Here's": {"a": 1}, "guide": {"to": 1}, "getting": {"in": 1}, "touch": {"with": 1}, "our": {"newsroom": 1, "patients,\"": 1}, "newsroom": {"and": 1}, "how": {"to": 1, "many": 1}, "sensitive": {"information.": 1}, "information.": {"$END$": 1}, "bill": {"House": 1}, "House": {"Democrats'": 1, "in": 1}, "Democrats'": {"will": 1}, "vote": {"on": 1}, "would": {"establish": 1}, "establish": {"automatic": 1}, "automatic": {"voter": 1}, "voter": {"registration,": 1}, "registration,": {"strengthen": 1}, "strengthen": {"the": 1}, "Voting": {"Rights": 1}, "Rights": {"Act,": 1}, "Act,": {"limit": 1}, "limit": {"partisan": 1}, "partisan": {"redistricting": 1}, "redistricting": {"and": 1}, "tighten": {"campaign": 1}, "campaign": {"finance": 1}, "finance": {"laws.": 1}, "laws.": {"$END$": 1}, "Earlier": {"this": 1}, "fall,": {"needles": 1}, "needles": {"were": 1}, "repeatedly": {"found": 1}, "found": {"inside": 1, "his": 1}, "strawberries": {"sold": 1}, "sold": {"at": 1}, "grocery": {"stores.": 1}, "stores.": {"Now": 1}, "Now": {"a": 2}, "50-year-old": {"Berry": 1}, "Berry": {"Licious": 1}, "Licious": {"employee": 1}, "employee": {"is": 1}, "being": {"prosecuted": 1}, "prosecuted": {"and": 1}, "jail": {"if": 1}, "if": {"convicted.": 1, "the": 1}, "convicted.": {"$END$": 1}, "clips": {"from": 1}, "memoir,": {"set": 1}, "set": {"to": 1}, "hit": {"shelves": 1}, "shelves": {"Tuesday,": 1}, "Tuesday,": {"the": 1, "some": 1}, "lady": {"reads": 1}, "reads": {"about": 1}, "life": {"at": 1}, "Princeton": {"and": 1}, "difficulties": {"having": 1}, "having": {"a": 1}, "baby.": {"$END$": 1}, "After": {"10": 1, "decades,": 1, "years": 1}, "updated": {"its": 1}, "physical": {"activity": 1}, "activity": {"advice.": 1}, "advice.": {"The": 1}, "message?": {"Every": 1}, "Every": {"little": 1}, "little": {"bit": 1}, "bit": {"of": 1}, "movement": {"helps": 1}, "helps": {"you": 1}, "you": {"stay": 1}, "healthy": {"and": 1}, "better": {"than": 1}, "sitting": {"on": 1}, "couch.": {"$END$": 1}, "A": {"chemical": 1, "Kazakh": 1}, "chemical": {"in": 1}, "common": {"paint": 1}, "paint": {"removal": 1}, "removal": {"products": 1}, "implicated": {"in": 1}, "50": {"deaths.": 1}, "deaths.": {"Even": 1}, "Even": {"though": 1}, "federal": {"ban": 1}, "ban": {"has": 1}, "delayed,": {"some": 1}, "some": {"major": 1, "of": 1}, "major": {"retailers": 1, "government": 1}, "retailers": {"are": 1}, "voluntarily": {"taking": 1}, "taking": {"the": 1, "widely": 1}, "off": {"shelves.": 1}, "shelves.": {"$END$": 1}, "Rain": {"was": 1}, "best": {"known": 1}, "eerie,": {"sonorous": 1}, "sonorous": {"voice": 1}, "voice": {"he": 1}, "he": {"lent": 1, "was": 1}, "lent": {"to": 1}, "HAL": {"9000": 1}, "9000": {"in": 1}, "1968": {"Stanley": 1}, "Stanley": {"Kubrick": 1}, "Kubrick": {"film.": 1}, "film.": {"However,": 1}, "However,": {"he": 1}, "also": {"celebrated": 1, "found.": 1}, "celebrated": {"for": 1}, "decades": {"of": 1, "the": 1}, "performances": {"on": 1}, "Shakespearean": {"stage.": 1}, "stage.": {"$END$": 1}, "decades,": {"a": 1}, "Connecticut": {"man": 1}, "man": {"found": 1}, "grandfather's": {"grave": 1}, "grave": {"in": 1}, "Netherlands,": {"and": 1}, "Dutch": {"family": 1}, "family": {"members": 1}, "members": {"that": 1}, "grave's": {"volunteer": 1}, "volunteer": {"caretakers.": 1}, "caretakers.": {"$END$": 1}, "Kazakh": {"rights": 1}, "rights": {"organization": 1}, "organization": {"has": 1}, "collected": {"more": 1}, "1,000": {"testimonies": 1}, "testimonies": {"from": 1}, "ethnic": {"Kazakhs": 1}, "Kazakhs": {"and": 1}, "Uighurs": {"whose": 1}, "whose": {"families": 1}, "families": {"have": 1}, "disappeared": {"into": 1}, "internment": {"camps": 1}, "camps": {"in": 1}, "Xinjiang.": {"$END$": 1}, "Two": {"new": 1}, "studies": {"offer": 1}, "unexpected": {"insights": 1}, "insights": {"\u00e2\u0080\u0094": 1}, "\u00e2\u0080\u0094": {"and": 1, "into": 1}, "solutions": {"\u00e2\u0080\u0094": 1}, "problem": {"of": 1}, "spousal": {"abuse.": 1}, "abuse.": {"$END$": 1}, "11,": {"2018": 10}, "Trump": {"administration": 1}, "administration": {"hopes": 1}, "hopes": {"the": 1, "to": 1}, "sanctions": {"will": 1}, "force": {"Iran": 1}, "negotiate": {"a": 1}, "nuclear": {"deal.": 1}, "deal.": {"But": 1}, "But": {"analysts": 1, "the": 1, "how": 1}, "analysts": {"point": 1}, "point": {"out": 1}, "out": {"there": 1}, "there": {"are": 1}, "overt": {"and": 1}, "covert": {"activities": 1}, "activities": {"to": 1}, "avoid": {"the": 1}, "penalties.": {"$END$": 1}, "speech": {"at": 1}, "Arc": {"de": 1}, "de": {"Triomphe,": 1}, "Triomphe,": {"French": 1}, "French": {"President": 1}, "President": {"Emmanuel": 1, "Trump.": 1}, "Emmanuel": {"Macron": 1}, "Macron": {"took": 1}, "took": {"aim": 1}, "aim": {"at": 1}, "style": {"of": 1}, "nationalism": {"that": 1}, "embraced": {"by": 1}, "Trump.": {"$END$": 1}, "Thanks": {"to": 1}, "mix": {"of": 1}, "retirements": {"and": 1}, "defeats": {"on": 1}, "high-profile": {"lawmakers": 1}, "lawmakers": {"will": 1}, "soon": {"be": 1}, "be": {"exiting": 1}, "exiting": {"Capitol": 1}, "Capitol": {"Hill,": 1}, "Hill,": {"from": 1}, "Paul": {"Ryan": 1}, "Ryan": {"to": 1}, "Beto": {"O'Rourke": 1}, "O'Rourke": {"to": 1}, "Claire": {"McCaskill.": 1}, "McCaskill.": {"$END$": 1}, "\"We": {"are": 1}, "anti-gun:": {"we": 1}, "anti-bullet": {"holes": 1}, "holes": {"in": 1}, "patients,\"": {"wrote": 1}, "wrote": {"one": 1}, "one": {"physician": 1, "of": 1}, "physician": {"in": 1}, "response": {"to": 1}, "NRA.": {"Another": 1}, "Another": {"posted": 1}, "posted": {"a": 1}, "photo": {"of": 1}, "own": {"scrubs,": 1}, "scrubs,": {"bloody": 1}, "bloody": {"from": 1}, "save": {"a": 1}, "gunshot": {"victim.": 1}, "victim.": {"$END$": 1}, "past": {"year,": 1}, "year,": {"NPR's": 1, "leaving": 1}, "NPR's": {"Leila": 1}, "Leila": {"Fadel": 1}, "Fadel": {"has": 1}, "report": {"on": 1}, "mass": {"shooting": 1}, "shooting": {"in": 2}, "Las": {"Vegas,": 1}, "Vegas,": {"and": 1}, "last": {"week's": 1, "week.": 1}, "week's": {"shooting": 1}, "Thousand": {"Oaks,": 1}, "Oaks,": {"Calif.,": 1}, "Calif.,": {"that": 1}, "13": {"dead,": 1}, "dead,": {"including": 1}, "gunman.": {"$END$": 1}, "For": {"decades": 1}, "Navajo": {"Generating": 1, "and": 1}, "Generating": {"Station": 1}, "Station": {"provided": 1}, "provided": {"a": 1}, "good": {"livelihood": 1}, "livelihood": {"for": 1}, "Hopi": {"tribes.": 1}, "tribes.": {"But": 1}, "plant": {"is": 1}, "scheduled": {"to": 1}, "close": {"next": 1}, "next": {"year,": 1}, "leaving": {"500": 1}, "500": {"workers": 1}, "workers": {"scrambling": 1}, "scrambling": {"for": 1}, "alternative.": {"$END$": 1}, "Rare": {"mummified": 1}, "mummified": {"scarabs,": 1}, "scarabs,": {"preserved": 1}, "preserved": {"in": 1}, "coffins": {"decorated": 1}, "decorated": {"with": 1}, "beetle": {"drawings,": 1}, "drawings,": {"were": 1}, "Egypt": {"hopes": 1}, "attract": {"visitors": 1}, "visitors": {"to": 1}, "country's": {"heritage": 1}, "heritage": {"sites,": 1}, "sites,": {"where": 1}, "where": {"tourism": 1}, "tourism": {"has": 1}, "dropped": {"since": 1}, "since": {"2011.": 1}, "2011.": {"$END$": 1}, "Republican": {"Dan": 1}, "Dan": {"Crenshaw": 1, "Crenshaw's": 1}, "Crenshaw": {"is": 1, "stopped": 1}, "16": {"veterans": 1}, "veterans": {"who": 1}, "newly": {"elected": 2}, "elected": {"to": 1, "congressman": 1}, "midterm": {"elections.": 1}, "elections.": {"$END$": 1}, "Outdoor": {"cats": 1}, "kill": {"as": 1}, "many": {"as": 1, "cats": 1}, "4": {"billion": 1}, "birds": {"each": 1}, "each": {"year": 1}, "year": {"in": 1}, "country.": {"But": 1}, "there,": {"really?": 1}, "really?": {"Now": 1}, "team": {"of": 1}, "technicians": {"is": 1}, "count": {"Washington,": 1}, "Washington,": {"D.C.'s": 1}, "D.C.'s": {"feral": 1}, "feral": {"felines.": 1}, "felines.": {"$END$": 1}, "Pete": {"Davidson": 1}, "Davidson": {"made": 1, "\"looks": 1}, "made": {"fun": 1}, "fun": {"of": 1}, "congressman": {"Dan": 1}, "Crenshaw's": {"eye": 1}, "eye": {"patch": 1}, "patch": {"last": 1}, "week.": {"Crenshaw": 1}, "stopped": {"by": 1}, "week": {"to": 1, "after": 1}, "\"looks": {"like": 1}, "meth": {"from": 1}, "Breaking": {"Bad": 1}, "Bad": {"was": 1}, "person.\"": {"$END$": 1}, "10,": {"2018": 2}, "Machine": {"counting": 1}, "counting": {"of": 1}, "votes": {"will": 1}, "begin": {"this": 1}, "narrow": {"margins": 1}, "margins": {"were": 1}, "reported": {"in": 1}, "races": {"for": 1}, "governor": {"and": 1}, "Senate.": {"$END$": 1}, "debate,": {"a": 1}, "funded": {"study": 1}, "failed": {"to": 1}, "find": {"any": 1}, "overall": {"benefit": 1}, "benefit": {"of": 1}, "widely": {"used": 1}, "used": {"supplements": 1}, "supplements": {"to": 1}, "protect": {"against": 1}, "heart": {"disease": 1}, "disease": {"or": 1}, "or": {"cancer.": 1}, "cancer.": {"$END$": 1}}